redis_decorators/__init__.py
redis_decorators/cache_element.py
redis_decorators/cacheable.py
redis_decorators/caching.py
redis_decorators/testing.py
tests/__init__.py
tests/conftest.py
tests/test_caching.py
redis_decorators-1.0.1.dist-info/LICENSE
redis_decorators-1.0.1.dist-info/METADATA
redis_decorators-1.0.1.dist-info/WHEEL
redis_decorators-1.0.1.dist-info/top_level.txt
redis_decorators-1.0.1.dist-info/RECORD
